COPYING
MANIFEST.in
MQ2.spec
MQ2_doc.pdf
README.rst
setup.py
MQ2/__init__.py
MQ2/add_marker_to_qtls.py
MQ2/add_qtl_to_map.py
MQ2/mapchart.py
MQ2/mq2.py
MQ2/plugin_interface.py
MQ2/qtl.py
MQ2.egg-info/PKG-INFO
MQ2.egg-info/SOURCES.txt
MQ2.egg-info/dependency_links.txt
MQ2.egg-info/entry_points.txt
MQ2.egg-info/requires.txt
MQ2.egg-info/top_level.txt
MQ2/plugins/__init__.py
MQ2/plugins/csv_plugin.py
MQ2/plugins/mapqtl_plugin.py
MQ2/plugins/xls_plugin.py
doc/Makefile
doc/conf.py
doc/contribute.rst
doc/data.rst
doc/index.rst
doc/install.rst
doc/make.bat
doc/output.rst
doc/plugin.rst
doc/usage.rst
test/MapChart.map
test/MapChart.map~
test/__init__.py
test/__init__.pyc
test/map.csv
test/map_with_qtls.csv
test/qtls.csv
test/qtls_matrix.csv
test/qtls_with_mk.csv
test/test.py
test/test.pyc
test/test_csv.py
test/test_csv.pyc
test/test_mapqtl.py
test/test_mapqtl.pyc
test/test_xls.py
test/test_xls.pyc